uzbek_stemmer/__init__.py
uzbek_stemmer/__main__.py
uzbek_stemmer/cli.py
uzbek_stemmer/helloworld.py
uzbek_stemmer-0.0.1.dist-info/AUTHORS.rst
uzbek_stemmer-0.0.1.dist-info/LICENSE
uzbek_stemmer-0.0.1.dist-info/METADATA
uzbek_stemmer-0.0.1.dist-info/WHEEL
uzbek_stemmer-0.0.1.dist-info/entry_points.txt
uzbek_stemmer-0.0.1.dist-info/top_level.txt
uzbek_stemmer-0.0.1.dist-info/RECORD
