Metadata-Version: 2.1
Name: uzbek-stemmer
Version: 0.0.1
Summary: Stemming tool for Uzbek language
Home-page: https://github.com/SanatbekMatlatipov/python-uzbek-stemmer
Author: Sanatbek Matlatipov
Author-email: mr.sanatbek@gmail.com
License: Apache-2.0
Project-URL: Documentation, https://uzbek-stemmer.readthedocs.io/
Project-URL: Changelog, https://uzbek-stemmer.readthedocs.io/en/latest/changelog.html
Project-URL: Issue Tracker, https://github.com/SanatbekMatlatipov/python-uzbek-stemmer/issues
Platform: UNKNOWN
Classifier: Development Status :: 5 - Production/Stable
Classifier: Intended Audience :: Developers
Classifier: License :: OSI Approved :: Apache Software License
Classifier: Operating System :: Unix
Classifier: Operating System :: POSIX
Classifier: Operating System :: Microsoft :: Windows
Classifier: Programming Language :: Python
Classifier: Programming Language :: Python :: 3
Classifier: Programming Language :: Python :: 3 :: Only
Classifier: Programming Language :: Python :: 3.6
Classifier: Programming Language :: Python :: 3.7
Classifier: Programming Language :: Python :: 3.8
Classifier: Programming Language :: Python :: 3.9
Classifier: Programming Language :: Python :: Implementation :: CPython
Classifier: Programming Language :: Python :: Implementation :: PyPy
Classifier: Topic :: Utilities
Requires-Python: >=3.6
